README.rst
setup.cfg
setup.py
ffire/__init__.py
ffire.egg-info/PKG-INFO
ffire.egg-info/SOURCES.txt
ffire.egg-info/dependency_links.txt
ffire.egg-info/not-zip-safe
ffire.egg-info/requires.txt
ffire.egg-info/top_level.txt
ffire/constants/__init__.py
ffire/constants/all.py
ffire/constants/broker_info.py
ffire/constants/fake.py
ffire/constants/time_intervals.py
ffire/core/__init__.py
ffire/core/fire.py
ffire/core/messages.py
ffire/core/utils.py
ffire/exc/__init__.py
ffire/exc/failed.py
ffire/exc/invalid.py
ffire/exc/missing.py