Metadata-Version: 1.1
Name: ffire
Version: 0.1.0
Summary: GUI Style Events for Web Applications
Home-page: http://github.com/ffireio/ffire-python
Author: Raymond Ortserga
Author-email: r.ortserga@fetchr.us
License: MIT
Keywords: Events Publish Subscribe Fire Raise Web API
Platform: UNKNOWN
Classifier: Development Status :: 4 - Beta
Classifier: Programming Language :: Python :: 2.6
Classifier: Programming Language :: Python :: 2.7
Classifier: Programming Language :: Python :: 3
Classifier: Programming Language :: Python :: 3.3
Classifier: Programming Language :: Python :: 3.4
Classifier: Programming Language :: Python :: 3.5
Classifier: Programming Language :: Python :: Implementation :: CPython
Classifier: Topic :: Communications
Classifier: Topic :: Internet
Classifier: Topic :: Software Development :: Libraries :: Application Frameworks
